gdn_health_check/__init__.py
gdn_health_check/solr/__init__.py
gdn_health_check/solr/apps.py
gdn_health_check/solr/backends.py
gdn_health_check-0.0.1.dist-info/METADATA
gdn_health_check-0.0.1.dist-info/WHEEL
gdn_health_check-0.0.1.dist-info/top_level.txt
gdn_health_check-0.0.1.dist-info/RECORD
